[{"data": {"ATT": {"periodic-4": 0.6496359882, "periodic-0.1": 0.3503640118}, "DEF": {"probeCountTime-4_10": 0.5290060162, "probeCountTime-3_10": 0.4709939838}}, "type": "GA_Profile"}, {"data": {"ATT": {"periodic-0.1": 0.2632967611, "periodicDecept-20_27": 0.7367032389}, "DEF": {"probeCountTime-1_10": 0.5912118778, "probeCountTime-2_50": 0.4087881222}}, "type": "GA_Profile"}, {"data": {"ATT": {"periodic-4": 0.0061981104, "periodic-0.1": 0.2808566397, "periodicDecept-20_27": 0.7129452499}, "DEF": {"probeCountTime-2_10": 0.4792813173, "probeCountTime-1_10": 0.066737752, "probeCountTime-2_50": 0.4539809308}}, "type": "GA_Profile"}]