[{"data": {"ATT": {"periodic-4": 0.6496359882, "periodic-0.1": 0.3503640118}, "DEF": {"probeCountTime-4_10": 0.5290060162, "probeCountTime-3_10": 0.4709939838}}, "type": "GA_Profile"}, {"data": {"ATT": {"periodicDecept-17_1": 0.6011252522, "periodic-0.1": 0.3988747478}, "DEF": {"probeCountTime-1_10": 0.6025489254, "probeCountTime-2_50": 0.3974510746}}, "type": "GA_Profile"}, {"data": {"ATT": {"periodicDecept-17_1": 0.6008454594, "periodic-4": 8.94569e-05, "periodic-0.1": 0.3990650837}, "DEF": {"probeCountTime-2_10": 0.4379573239, "probeCountTime-1_10": 0.1204494194, "probeCountTime-2_50": 0.4415932568}}, "type": "GA_Profile"}]