[{"data": {"ATT": {"periodic-15": 0.5769169526, "periodic-0.1": 0.4230830474}, "DEF": {"probeCountTime-2_10": 0.5386745502, "probeCountTime-2_50": 0.4613254498}}, "type": "GA_Profile"}, {"data": {"ATT": {"periodic-20": 0.7364358658, "periodic-0.1": 0.2635641342}, "DEF": {"probeCountTime-1_10": 0.5912103762, "probeCountTime-2_50": 0.4087896238}}, "type": "GA_Profile"}, {"data": {"ATT": {"periodic-15": 0.5216881155, "periodic-0.1": 0.4101053012, "periodic-20": 0.0682065833}, "DEF": {"probeCountTime-2_10": 0.4279669645, "probeCountTime-1_10": 0.1229953836, "probeCountTime-2_50": 0.449037652}}, "type": "GA_Profile"}]