[{"data": {"ATT": {"periodicDecept-5_13": 1.0}, "DEF": {"periodic-15": 1.0}}, "type": "GA_Profile"}, {"data": {"ATT": {"periodicMax-20": 0.2110234812, "periodicDecept-17_5": 0.7889765188}, "DEF": {"probeCountTime-2_50": 0.8042815677, "probeCountTime-2_100": 0.1957184323}}, "type": "GA_Profile"}, {"data": {"ATT": {"periodicMax-20": 0.0983077504, "periodicDecept-5_13": 0.5704761099, "periodicDecept-17_5": 0.3312161396}, "DEF": {"probeCountTime-4_10": 0.6468858155, "probeCountTime-2_50": 0.3045425908, "probeCountTime-2_100": 0.0485715937}}, "type": "GA_Profile"}]