[{"data": {"ATT": {"periodic-0.1": 0.2272093484, "periodicDecept-5_1": 0.7727906516}, "DEF": {"probeCountTime-4_10": 0.6084660206, "probeCountTime-3_10": 0.3915339794}}, "type": "GA_Profile"}, {"data": {"ATT": {"periodic-0.1": 0.2085091393, "periodicMax-11": 0.0824072733, "periodicDecept-5_1": 0.7090835874}, "DEF": {"probeCountTime-4_10": 0.0820200119, "probeCountTime-3_10": 0.828370038, "probeCountTime-3_50": 0.0896099501}}, "type": "GA_Profile"}, {"data": {"ATT": {"periodic-0.1": 0.5754397501, "periodicMax-11": 0.4245602499}, "DEF": {"probeCountTime-2_10": 0.5387487377, "probeCountTime-2_50": 0.4612512623}}, "type": "GA_Profile"}]